{
  "test": [
    {
      "id": "0",
      "msg": "abc"
    }
  ],
  "light": [
    {
      "date": "Dec 30, 2019",
      "time": "19:10:38",
      "value": "50",
      "set": "65",
      "id": "_4l_VoW"
    },
    {
      "date": "Dec 30, 2019",
      "time": "19:14:09",
      "value": "50",
      "set": "65",
      "id": "Anu7oLK"
    },
    {
      "date": "Dec 30, 2019",
      "time": "19:14:12",
      "value": "50",
      "set": "65",
      "id": "iAMvzJ0"
    },
    {
      "date": "Dec 30, 2019",
      "time": "19:17:55",
      "value": "50",
      "set": "65",
      "id": "KZSNXJ0"
    },
    {
      "date": "Dec 30, 2019",
      "time": "19:17:58",
      "value": "50",
      "set": "65",
      "id": "aGc_1cr"
    },
    {
      "date": "Dec 30, 2019",
      "time": "19:18:01",
      "value": "50",
      "set": "65",
      "id": "04FaVL5"
    },
    {
      "date": "Dec 30, 2019",
      "time": "19:18:04",
      "value": "50",
      "set": "65",
      "id": "jgrJBsD"
    },
    {
      "date": "Dec 30, 2019",
      "time": "19:18:07",
      "value": "50",
      "set": "65",
      "id": "dDIUQEt"
    },
    {
      "date": "Dec 30, 2019",
      "time": "19:18:10",
      "value": "50",
      "set": "65",
      "id": "wGRA74H"
    },
    {
      "date": "Dec 30, 2019",
      "time": "19:18:13",
      "value": "50",
      "set": "65",
      "id": "kevn_6Q"
    },
    {
      "date": "Dec 30, 2019",
      "time": "19:20:07",
      "value": "50",
      "set": "65",
      "id": "sH5leA8"
    },
    {
      "date": "Dec 30, 2019",
      "time": "19:20:10",
      "value": "50",
      "set": "65",
      "id": "1r4XHoI"
    }
  ],
  "temperature": [
    {
      "date": "Dec 30, 2019",
      "time": "19:10:32",
      "value": "33",
      "set": "34",
      "id": "5BYJZH2"
    },
    {
      "date": "Dec 30, 2019",
      "time": "19:14:09",
      "value": "34",
      "set": "34",
      "id": "lzk3o0B"
    },
    {
      "date": "Dec 30, 2019",
      "time": "19:14:12",
      "value": "33",
      "set": "34",
      "id": "51CWs3n"
    },
    {
      "date": "Dec 30, 2019",
      "time": "19:17:55",
      "value": "34",
      "set": "34",
      "id": "xINmUMP"
    },
    {
      "date": "Dec 30, 2019",
      "time": "19:17:58",
      "value": "33",
      "set": "34",
      "id": "ENE_58S"
    },
    {
      "date": "Dec 30, 2019",
      "time": "19:18:01",
      "value": "32",
      "set": "34",
      "id": "2rW4W7m"
    },
    {
      "date": "Dec 30, 2019",
      "time": "19:18:04",
      "value": "33",
      "set": "34",
      "id": "4OUQN-L"
    },
    {
      "date": "Dec 30, 2019",
      "time": "19:18:07",
      "value": "33",
      "set": "34",
      "id": "tP5Q5df"
    },
    {
      "date": "Dec 30, 2019",
      "time": "19:18:10",
      "value": "32",
      "set": "34",
      "id": "Orb90vO"
    },
    {
      "date": "Dec 30, 2019",
      "time": "19:18:13",
      "value": "32",
      "set": "34",
      "id": "kuH7GCv"
    },
    {
      "date": "Dec 30, 2019",
      "time": "19:20:07",
      "value": "34",
      "set": "34",
      "id": "bAFWd9_"
    },
    {
      "date": "Dec 30, 2019",
      "time": "19:20:10",
      "value": "33",
      "set": "34",
      "id": "gvi_XPR"
    }
  ],
  "water": [
    {
      "date": "Dec 30, 2019",
      "time": "19:10:32",
      "value": "36",
      "set": "20",
      "id": "Y1J29GK"
    },
    {
      "date": "Dec 30, 2019",
      "time": "19:14:09",
      "value": "2892",
      "set": "20",
      "id": "LCzwe7k"
    },
    {
      "date": "Dec 30, 2019",
      "time": "19:14:12",
      "value": "11136",
      "set": "20",
      "id": "-vuIDzM"
    },
    {
      "date": "Dec 30, 2019",
      "time": "19:17:55",
      "value": "2871",
      "set": "20",
      "id": "h0_hC8K"
    },
    {
      "date": "Dec 30, 2019",
      "time": "19:17:58",
      "value": "11144",
      "set": "20",
      "id": "lktjSNk"
    },
    {
      "date": "Dec 30, 2019",
      "time": "19:18:01",
      "value": "11143",
      "set": "20",
      "id": "3DkmpQV"
    },
    {
      "date": "Dec 30, 2019",
      "time": "19:18:04",
      "value": "11136",
      "set": "20",
      "id": "bYvD1t6"
    },
    {
      "date": "Dec 30, 2019",
      "time": "19:18:07",
      "value": "11137",
      "set": "20",
      "id": "YslpH4I"
    },
    {
      "date": "Dec 30, 2019",
      "time": "19:18:10",
      "value": "2881",
      "set": "20",
      "id": "PlZcqaS"
    },
    {
      "date": "Dec 30, 2019",
      "time": "19:18:13",
      "value": "11136",
      "set": "20",
      "id": "UTh-GYn"
    },
    {
      "date": "Dec 30, 2019",
      "time": "19:20:07",
      "value": "11136",
      "set": "20",
      "id": "8qU7a0Y"
    },
    {
      "date": "Dec 30, 2019",
      "time": "19:20:10",
      "value": "11136",
      "set": "20",
      "id": "qeCppux"
    }
  ],
  "preferences": [
    {
      "id": 0,
      "current": "Alaskan Thunderfuck",
      "currentId": 5,
      "light": "65",
      "temperature": "34",
      "water": "20"
    },
    {
      "id": 1,
      "name": "Barck O Bubba",
      "light": "54",
      "temperature": "40",
      "water": "24"
    },
    {
      "id": 2,
      "name": "Poochie Love",
      "light": "53",
      "temperature": "36",
      "water": "23"
    },
    {
      "id": 3,
      "name": "Purple Monkey Balls",
      "light": "59",
      "temperature": "32",
      "water": "22"
    },
    {
      "id": 4,
      "name": "Cannasutra",
      "light": "60",
      "temperature": "41",
      "water": "21"
    },
    {
      "id": 5,
      "name": "Alaskan Thunderfuck",
      "light": "65",
      "temperature": "34",
      "water": "20"
    }
  ]
}